salt_ssh_keygen/__init__.py
salt_ssh_keygen/modules/__init__.py
salt_ssh_keygen/modules/keygen.py
salt_ssh_keygen/states/__init__.py
salt_ssh_keygen/states/keygen.py
salt_ssh_keygen-0.1.0.dist-info/WHEEL
salt_ssh_keygen-0.1.0.dist-info/entry_points.txt
salt_ssh_keygen-0.1.0.dist-info/METADATA
salt_ssh_keygen-0.1.0.dist-info/RECORD
