Metadata-Version: 2.4
Name: salt-ssh-keygen
Version: 0.1.0
Summary: Helpers for ssh-keygen with Saltstack
Author: Paul
Author-email: Paul <kungfudiscomonkey@gmail.com>
License-Expression: MIT
Classifier: Development Status :: 3 - Alpha
Classifier: Programming Language :: Python :: 3.10
Classifier: Programming Language :: Python :: 3.11
Classifier: Programming Language :: Python :: 3.12
Classifier: Programming Language :: Python :: 3.13
Classifier: Programming Language :: Python :: 3.14
Classifier: Programming Language :: Python :: 3.15
Requires-Dist: salt>=3006
Requires-Python: >=3.10
Project-URL: issues, https://codeberg.org/kfdm/salt-ssh-keygen/issues
Project-URL: source, https://codeberg.org/kfdm/salt-ssh-keygen
